{
  "title": "Moja prva objava",
  "subtitle": "Moj prvi podnaslov",
  "author": "Jakob Marušič",
  "category": "Novice",
  "cover": "/img/347634745_804599627855062_8545003673725528087_n.jpg",
  "summary": "T﻿o je kratek povzetek prve novice. Povzetek objave bo prikazan na seznamu vseh novic. Ravno tako ga bomo mogoče v neki točki uporabljali za SEO, zato je bistvenega pomena da je res kratek.",
  "body": "**T﻿o je vsebina.**\n\nV﻿sebina je lahko ZELOOOOOO dolga.\n\n\n\nA﻿li pa kratka - toda ne prekratka, ker je drugače novica brez vsebine. To pa ni ok.\n\n\n\nV﻿sebina ima lahko tudi slike - a ni to fajn?\n\n\n\n![](/img/347269340_761751668759482_5891382283528008371_n.jpg)"
}